Workbook

Sheet Start Here
A1: Ride YourWay Prospective Market Intake Template
A3: Use this workbook with prospective hospitals, skilled nursing facilities, brokers, health plans, and community organizations. The goal is to collect consistent demand, pricing, and billing-policy information that can be rolled into Ride YourWay's master market-readiness model.
A6: How to complete this workbook
A7: 1. Fill out the blue cells on 'Organization Intake' for one organization / contract.
A8: 2. On 'Trip Demand Input', enter one row for each distinct trip pattern, program, or service line.
A9: 3. Use average weekly demand if historical trip-level data is not available.
A10: 4. Keep completed trips, billable no-shows, and non-billable no-shows separate.
A11: 5. Leave formulas and gray cells unchanged; they summarize what you entered.
A14: Why these inputs matter
A15: Trip density & daily pattern | B15: Helps estimate whether vehicles can be utilized efficiently across the week.
A16: Billable no-show terms | B16: Ride YourWay needs to know when canceled or missed trips still generate revenue.
A17: Mode mix | B17: Wheelchair, Stretcher Alternative, and SecureCare materially affect economics.
A18: Quality vs filler / broker volume | B18: Predictable quality volume is preferred, but broker fill can improve density.
A19: Pricing / reimbursement | B19: Revenue thresholds are required to determine whether a market can support launch.
A22: Ride YourWay launch-readiness thresholds (reference)
A23: Vehicle utilization | B23: 95%+ | C23: These thresholds come from Ride YourWay's validated operating criteria. Most of them are calculated in the master model after intake data is combined.
A24: Billed utilization | B24: 105%+
A25: Total volume pool | B25: 120% with proper mix
A26: Average revenue per Kent-Leg | B26: $70+
A27: Higher-acuity share | B27: 5%+ of volume
A28: Road time per vehicle per day | B28: 9+ hours
A30: Single-contract concentration | B30: <=20% of volume or revenue
A33: Color legend
A34: Blue text / light blue cells | B34: External input required
A35: Black text / light gray cells | B35: Formula or auto-calculated summary
A36: Orange cells | B36: Review or unusual item
A37: Gray labels | B37: Instructions / static fields

Sheet Organization Intake
A1: Organization / Contract Intake
A3: Complete one workbook per prospective organization or contract.
A5: Organization details
A6: Submission ID | B6: Ex-CEO-001 | C6: Organization name | D6: Example MEdical Center | E6: Organization Type | F6: Hospital
A7: Facility / program name | B7: Care Access Program | C7: Primary service area / market | D7: Grand Rapids | E7: Primary city, state | F7: Grand Rapids, Michigan
A8: Primary contact name | B8: Bilbo Baggins | C8: Title | D8: Director of Care Coordination | E8: Email
A9: Phone | C9: Data period start | E9: Data period end
A11: Commercial terms & service profile
A12: Contract / payer name | C12: Payer type | E12: Expected go-live timing
A13: Primary source of trips | C13: Default billing basis | E13: Average payment term (days)
A14: Trip scheduling lead time | C14: Billable no-show allowed? | E14: Billable late cancel?
A15: Ambulatory avg price / trip | C15: Wheelchair avg price / trip | E15: Stretcher Alt. avg price / trip
A16: SecureCare avg price / trip | C16: Other mode avg price / trip | E16: Other mode description
A18: Known constraints / notes
A19: Typical destinations / facilities served
A20: Known access, hours, or handoff constraints
A21: Additional comments
A25: Auto-checks
A26: Intake completion status | B26: =IF(COUNTA(B6,D6,F6,B8,F8,B12,D12,D14,F14)=9,"Complete core fields","Missing core fields") -> Missing core fields
A27: Billable protection present? | B27: =IF(OR(D14="Yes",F14="Yes"),"Yes","No") -> No
A28: Higher-acuity pricing entered? | B28: =IF(OR(F15<>"",B16<>""),"Yes","No") -> No

Sheet Trip Demand Input
A1: Trip Demand Input (one row per trip pattern / service line / program)
A3: Enter average weekly demand by pattern. Keep completed trips, billable no-shows, and non-billable no-shows separate.
A5: Row ID | B5: Facility Name | C5: Contract / Program | D5: Source Type | E5: Volume Class | F5: Service Category | G5: Trip Mode | H5: Higher-Acuity? | I5: Pickup Zone / ZIP | J5: Dropoff Zone / ZIP | K5: Avg One-Way Miles | L5: Completed Trips / Week | M5: Billable No-Shows / Week | N5: Non-Billable No-Shows / Week | O5: Mon | P5: Tue | Q5: Wed | R5: Thu | S5: Fri | T5: Sat | U5: Sun | V5: Avg Revenue / Completed Trip | W5: Recurring? | X5: Booking Notice (hrs) | Y5: Notes | Z5: Weekly Total (days) | AA5: Billed Trips / Week | AB5: Non-Billable NS % | AC5: Billed Utilization Index | AD5: Revenue / Week | AE5: HA Trips / Week | AF5: Row Status
A6: 1 | B6: Example Medical Center | C6: ED / Inpatient Discharges - Wheelchairs | D6: Hospital | E6: Quality | F6: Discharge | G6: Wheelchair | H6: No | K6: 9 | L6: 18 | M6: 2 | N6: 1 | O6: 3 | P6: 4 | Q6: 4 | R6: 3 | S6: 4 | T6: 1 | U6: 1 | V6: 200 | Z6: =IF(COUNTA(O6:U6)=0,"",SUM(O6:U6)) -> 20 | AA6: =IF(L6="","",L6+M6) -> 20 | AB6: =IF(SUM(L6:N6)=0,"",N6/SUM(L6:N6)) -> 0.047619048 | AC6: =IF(L6=0,"",(L6+M6)/L6) -> 1.1111111 | AD6: =IF(L6="","",L6*V6+M6*#REF!) -> #REF! | AE6: =IF(H6="Yes",L6,"")
A7: 2 | Z7: =IF(COUNTA(O7:U7)=0,"",SUM(O7:U7)) | AA7: =IF(L7="","",L7+M7) | AB7: =IF(SUM(L7:N7)=0,"",N7/SUM(L7:N7)) | AC7: =IF(L7=0,"",(L7+M7)/L7) | AD7: =IF(L7="","",L7*V7+M7*#REF!) | AE7: =IF(H7="Yes",L7,"")
A8: 3 | Z8: =IF(COUNTA(O8:U8)=0,"",SUM(O8:U8)) | AA8: =IF(L8="","",L8+M8) | AB8: =IF(SUM(L8:N8)=0,"",N8/SUM(L8:N8)) | AC8: =IF(L8=0,"",(L8+M8)/L8) | AD8: =IF(L8="","",L8*V8+M8*#REF!) | AE8: =IF(H8="Yes",L8,"")
A9: 4 | Z9: =IF(COUNTA(O9:U9)=0,"",SUM(O9:U9)) | AA9: =IF(L9="","",L9+M9) | AB9: =IF(SUM(L9:N9)=0,"",N9/SUM(L9:N9)) | AC9: =IF(L9=0,"",(L9+M9)/L9) | AD9: =IF(L9="","",L9*V9+M9*#REF!) | AE9: =IF(H9="Yes",L9,"")
A10: 5 | Z10: =IF(COUNTA(O10:U10)=0,"",SUM(O10:U10)) | AA10: =IF(L10="","",L10+M10) | AB10: =IF(SUM(L10:N10)=0,"",N10/SUM(L10:N10)) | AC10: =IF(L10=0,"",(L10+M10)/L10) | AD10: =IF(L10="","",L10*V10+M10*#REF!) | AE10: =IF(H10="Yes",L10,"")
A11: 6 | Z11: =IF(COUNTA(O11:U11)=0,"",SUM(O11:U11)) | AA11: =IF(L11="","",L11+M11) | AB11: =IF(SUM(L11:N11)=0,"",N11/SUM(L11:N11)) | AC11: =IF(L11=0,"",(L11+M11)/L11) | AD11: =IF(L11="","",L11*V11+M11*#REF!) | AE11: =IF(H11="Yes",L11,"")
A12: 7 | Z12: =IF(COUNTA(O12:U12)=0,"",SUM(O12:U12)) | AA12: =IF(L12="","",L12+M12) | AB12: =IF(SUM(L12:N12)=0,"",N12/SUM(L12:N12)) | AC12: =IF(L12=0,"",(L12+M12)/L12) | AD12: =IF(L12="","",L12*V12+M12*#REF!) | AE12: =IF(H12="Yes",L12,"")
A13: 8 | Z13: =IF(COUNTA(O13:U13)=0,"",SUM(O13:U13)) | AA13: =IF(L13="","",L13+M13) | AB13: =IF(SUM(L13:N13)=0,"",N13/SUM(L13:N13)) | AC13: =IF(L13=0,"",(L13+M13)/L13) | AD13: =IF(L13="","",L13*V13+M13*#REF!) | AE13: =IF(H13="Yes",L13,"")
A14: 9 | Z14: =IF(COUNTA(O14:U14)=0,"",SUM(O14:U14)) | AA14: =IF(L14="","",L14+M14) | AB14: =IF(SUM(L14:N14)=0,"",N14/SUM(L14:N14)) | AC14: =IF(L14=0,"",(L14+M14)/L14) | AD14: =IF(L14="","",L14*V14+M14*#REF!) | AE14: =IF(H14="Yes",L14,"")
A15: 10 | Z15: =IF(COUNTA(O15:U15)=0,"",SUM(O15:U15)) | AA15: =IF(L15="","",L15+M15) | AB15: =IF(SUM(L15:N15)=0,"",N15/SUM(L15:N15)) | AC15: =IF(L15=0,"",(L15+M15)/L15) | AD15: =IF(L15="","",L15*V15+M15*#REF!) | AE15: =IF(H15="Yes",L15,"")
A16: 11 | Z16: =IF(COUNTA(O16:U16)=0,"",SUM(O16:U16)) | AA16: =IF(L16="","",L16+M16) | AB16: =IF(SUM(L16:N16)=0,"",N16/SUM(L16:N16)) | AC16: =IF(L16=0,"",(L16+M16)/L16) | AD16: =IF(L16="","",L16*V16+M16*#REF!) | AE16: =IF(H16="Yes",L16,"")
A17: 12 | Z17: =IF(COUNTA(O17:U17)=0,"",SUM(O17:U17)) | AA17: =IF(L17="","",L17+M17) | AB17: =IF(SUM(L17:N17)=0,"",N17/SUM(L17:N17)) | AC17: =IF(L17=0,"",(L17+M17)/L17) | AD17: =IF(L17="","",L17*V17+M17*#REF!) | AE17: =IF(H17="Yes",L17,"")
A18: 13 | Z18: =IF(COUNTA(O18:U18)=0,"",SUM(O18:U18)) | AA18: =IF(L18="","",L18+M18) | AB18: =IF(SUM(L18:N18)=0,"",N18/SUM(L18:N18)) | AC18: =IF(L18=0,"",(L18+M18)/L18) | AD18: =IF(L18="","",L18*V18+M18*#REF!) | AE18: =IF(H18="Yes",L18,"")
... A65: 60 | Z65: =IF(COUNTA(O65:U65)=0,"",SUM(O65:U65)) | AA65: =IF(L65="","",L65+M65) | AB65: =IF(SUM(L65:N65)=0,"",N65/SUM(L65:N65)) | AC65: =IF(L65=0,"",(L65+M65)/L65) | AD65: =IF(L65="","",L65*V65+M65*#REF!) | AE65: =IF(H65="Yes",L65,"")

Sheet Summary Preview
A1: Submission Summary Preview
A4: Organization summary
A5: Submission ID | B5: =IF('Organization Intake'!B6="","",'Organization Intake'!B6) -> Ex-CEO-001
A6: Organization name | B6: =IF('Organization Intake'!D6="","",'Organization Intake'!D6) -> Example MEdical Center
A7: Organization type | B7: =IF('Organization Intake'!F6="","",'Organization Intake'!F6) -> Hospital
A8: Contract / payer | B8: =IF('Organization Intake'!B12="","",'Organization Intake'!B12)
A11: Demand & pricing checks
A12: Completed trips / week | B12: =IF(COUNTA('Trip Demand Input'!B6:V65)=0,"",SUM('Trip Demand Input'!L6:L65)) -> 18
A13: Billable no-shows / week | B13: =IF(COUNTA('Trip Demand Input'!B6:V65)=0,"",SUM('Trip Demand Input'!M6:M65)) -> 2
A14: Non-billable no-shows / week | B14: =IF(COUNTA('Trip Demand Input'!B6:V65)=0,"",SUM('Trip Demand Input'!N6:N65)) -> 1
A15: Billed trips / week | B15: =IF(B12="","",B12+B13) -> 20
A16: Quality volume share | B16: =IF(B12=0,"",SUMIF('Trip Demand Input'!E6:E65,"Quality",'Trip Demand Input'!L6:L65)/B12) -> 1
A17: Broker + filler share | B17: =IF(B12=0,"",(SUMIF('Trip Demand Input'!E6:E65,"Broker",'Trip Demand Input'!L6:L65)+SUMIF('Trip Demand Input'!E6:E65,"Filler",'Trip Demand Input'!L6:L65))/B12) -> 0
A18: Higher-acuity share | B18: =IF(B12=0,"",SUM('Trip Demand Input'!AE6:AE65)/B12) -> 0
A19: Weighted avg revenue / completed trip | B19: =IF(B12=0,"",SUMPRODUCT('Trip Demand Input'!L6:L65,'Trip Demand Input'!V6:V65)/B12) -> 200
A20: Non-billable no-show rate | B20: =IF(SUM(B12:B14)=0,"",B14/SUM(B12:B14)) -> 0.047619048
A21: Total est. weekly revenue | B21: =IF(COUNTA('Trip Demand Input'!B6:V65)=0,"",SUM('Trip Demand Input'!AD6:AD65)) -> #REF!
A24: Threshold signal (reference only)
A25: Quality share >= 90% | B25: =IF(B16="","",IF(B16>=0.9,"Pass","Review")) -> Pass
A26: Broker/filler support present | B26: =IF(B17="","",IF(B17>=0.3,"Pass","Review")) -> Review
A27: Higher-acuity share >= 5% | B27: =IF(B18="","",IF(B18>=0.05,"Pass","Review")) -> Review
A28: Non-billable no-show rate < 10% | B28: =IF(B20="","",IF(B20<0.1,"Pass","Review")) -> Pass
A31: Note | B31: This preview checks only the organization submission. Vehicle utilization, road time, concentration risk across all contracts, and cost-per-road-hour are expected to be calculated in Ride YourWay's internal master workbook.

Sheet Lists
A1: Hospital | B1: Hospital | C1: Quality | D1: Discharge | E1: Ambulatory | F1: Yes | G1: Per Trip | H1: Direct Facility
A2: Skilled Nursing Facility | B2: SNF | C2: Filler | D2: Recurring Appointment | E2: Wheelchair | F2: No | G2: Per Leg | H2: Health Plan
A3: Health Plan | B3: Broker | C3: Broker | D3: Dialysis | E3: Stretcher Alternative | G3: Hourly | H3: Broker
A4: Broker | B4: Health Plan | C4: Other | D4: Facility Transfer | E4: SecureCare | G4: Capitated | H4: Community Program
A5: Community Organization | B5: Community Org | D5: Behavioral Health | E5: Other | G5: Other | H5: Other
A6: Behavioral Health | B6: Behavioral Health | D6: Community Program
A7: Other | B7: Other | D7: Other
